{"IcoMoonType":"selection","icons":[{"icon":{"paths":["M1024 608l-192-192v-288h-128v160l-192-192-512 512v32h128v320h320v-192h128v192h320v-320h128z"],"tags":["home","house"],"defaultCode":59650,"grid":16,"attrs":[]},"attrs":[],"properties":{"ligatures":"home3, house3","name":"home3","order":6,"id":0,"prevSize":32,"code":59650},"setIdx":0,"setId":2,"iconIdx":0},{"icon":{"paths":["M0 192l320-128v768l-320 128z","M384 32l320 192v736l-320-160z","M768 224l256-192v768l-256 192z"],"tags":["map","guide"],"defaultCode":59723,"grid":16,"attrs":[]},"attrs":[],"properties":{"ligatures":"map, guide","name":"map","order":7,"id":1,"prevSize":32,"code":59723},"setIdx":0,"setId":2,"iconIdx":1},{"icon":{"paths":["M448 128v-16c0-26.4-21.6-48-48-48h-160c-26.4 0-48 21.6-48 48v16h-192v128h192v16c0 26.4 21.6 48 48 48h160c26.4 0 48-21.6 48-48v-16h576v-128h-576zM256 256v-128h128v128h-128zM832 432c0-26.4-21.6-48-48-48h-160c-26.4 0-48 21.6-48 48v16h-576v128h576v16c0 26.4 21.6 48 48 48h160c26.4 0 48-21.6 48-48v-16h192v-128h-192v-16zM640 576v-128h128v128h-128zM448 752c0-26.4-21.6-48-48-48h-160c-26.4 0-48 21.6-48 48v16h-192v128h192v16c0 26.4 21.6 48 48 48h160c26.4 0 48-21.6 48-48v-16h576v-128h-576v-16zM256 896v-128h128v128h-128z"],"tags":["equalizer","sliders","settings","preferences","dashboard","control"],"defaultCode":59794,"grid":16,"attrs":[]},"attrs":[],"properties":{"ligatures":"equalizer, sliders","name":"equalizer","order":8,"id":2,"prevSize":32,"code":59794},"setIdx":0,"setId":2,"iconIdx":2},{"icon":{"paths":["M448 704h128v128h-128zM704 256c35.346 0 64 28.654 64 64v192l-192 128h-128v-64l192-128v-64h-320v-128h384zM512 96c-111.118 0-215.584 43.272-294.156 121.844s-121.844 183.038-121.844 294.156c0 111.118 43.272 215.584 121.844 294.156s183.038 121.844 294.156 121.844c111.118 0 215.584-43.272 294.156-121.844s121.844-183.038 121.844-294.156c0-111.118-43.272-215.584-121.844-294.156s-183.038-121.844-294.156-121.844zM512 0v0c282.77 0 512 229.23 512 512s-229.23 512-512 512c-282.77 0-512-229.23-512-512s229.23-512 512-512z"],"tags":["question","help","support"],"defaultCode":59913,"grid":16,"attrs":[]},"attrs":[],"properties":{"ligatures":"question, help","name":"question","order":9,"id":3,"prevSize":32,"code":59913},"setIdx":0,"setId":2,"iconIdx":3}],"height":1024,"metadata":{"name":"icomoon"},"preferences":{"showGlyphs":true,"showQuickUse":true,"showQuickUse2":true,"showSVGs":true,"fontPref":{"prefix":"icon-","metadata":{"fontFamily":"icomoon"},"metrics":{"emSize":1024,"baseline":6.25,"whitespace":50},"embed":false},"imagePref":{"prefix":"icon-","png":true,"useClassSelector":true,"color":0,"bgColor":16777215,"classSelector":".icon"},"historySize":50,"showCodes":true,"gridSize":16}}